mykaikeba_flow/__init__.py
mykaikeba_flow-0.0.4.dist-info/LICENSE
mykaikeba_flow-0.0.4.dist-info/METADATA
mykaikeba_flow-0.0.4.dist-info/WHEEL
mykaikeba_flow-0.0.4.dist-info/top_level.txt
mykaikeba_flow-0.0.4.dist-info/RECORD
